uproot_tree_utils/__init__.py
uproot_tree_utils/clone.py
uproot_tree_utils/write.py
uproot_tree_utils-0.2.dist-info/LICENSE
uproot_tree_utils-0.2.dist-info/METADATA
uproot_tree_utils-0.2.dist-info/WHEEL
uproot_tree_utils-0.2.dist-info/top_level.txt
uproot_tree_utils-0.2.dist-info/RECORD
