Metadata-Version: 2.1
Name: uproot-tree-utils
Version: 0.2
Summary: A small collection of utilities for handling ROOT TTrees with uproot.
Home-page: https://github.com/masonproffitt/uproot_tree_utils
Author: Mason Proffitt
Author-email: masonlp@uw.edu
License: UNKNOWN
Platform: UNKNOWN
Requires-Dist: numpy
Requires-Dist: uproot
